gql/__init__.py
gql/setup.py
gql/gql/__init__.py
gql/gql/client.py
gql/gql/datetime_utils.py
gql/gql/enum_utils.py
gql/gql/gql.py
gql/gql/graphql_client.py
gql/gql/reporter.py
gql/gql/utils.py
gql/gql/transport/__init__.py
gql/gql/transport/http.py
gql/gql/transport/local_schema.py
gql/gql/transport/session.py
gql/gql/transport/transport.py
gql/gql-checker/__init__.py
gql/gql-checker/setup.py
gql/gql-checker/gql_checker/__about__.py
gql/gql-checker/gql_checker/__init__.py
gql/gql-checker/gql_checker/flake8_linter.py
gql/gql-checker/gql_checker/pylama_linter.py
gql/gql-checker/gql_checker/stdlib_list.py
gql/gql-checker/tests/__init__.py
gql/gql-checker/tests/test_flake8_linter.py
gql/gql-checker/tests/test_pylama_linter.py
gql/gql-checker/tests/utils.py
gql/gql-checker/tests/test_cases/__init__.py
gql/gql-checker/tests/test_cases/bad_query.py
gql/gql-checker/tests/test_cases/noqa.py
gql/gql-checker/tests/test_cases/syntax_error.py
gql/gql-checker/tests/test_cases/validation.py
gql/tests/__init__.py
gql/tests/test_client.py
gql/tests/test_transport.py
gql/tests/starwars/__init__.py
gql/tests/starwars/fixtures.py
gql/tests/starwars/schema.py
gql/tests/starwars/test_dsl.py
gql/tests/starwars/test_query.py
gql/tests/starwars/test_validation.py
psym/__init__.py
psym/_utils.py
psym/exceptions.py
psym/api/__init__.py
psym/api/customer.py
psym/api/equipment.py
psym/api/equipment_type.py
psym/api/features.py
psym/api/file.py
psym/api/link.py
psym/api/location.py
psym/api/location_template.py
psym/api/location_type.py
psym/api/port.py
psym/api/port_type.py
psym/api/property_type.py
psym/api/service.py
psym/api/service_type.py
psym/api/user.py
psym/api/work_order_type.py
psym/graphql/__init__.py
psym/graphql/enum/__init__.py
psym/graphql/enum/cellular_network_type.py
psym/graphql/enum/check_list_item_enum_selection_mode.py
psym/graphql/enum/check_list_item_type.py
psym/graphql/enum/discovery_method.py
psym/graphql/enum/equipment_filter_type.py
psym/graphql/enum/file_type.py
psym-3.1.1.dist-info/METADATA
psym-3.1.1.dist-info/WHEEL
psym-3.1.1.dist-info/top_level.txt
psym-3.1.1.dist-info/RECORD
